racket_lab/__init__.py
racket_lab/advisor.py
racket_lab/racket.py
racket_lab-0.1.0.dist-info/METADATA
racket_lab-0.1.0.dist-info/WHEEL
racket_lab-0.1.0.dist-info/top_level.txt
racket_lab-0.1.0.dist-info/RECORD
