Metadata-Version: 2.4
Name: racket-lab
Version: 0.1.0
Summary: A Python library for tennis equipment physics and analytics
Home-page: https://github.com/LiwaaCoder/racket-lab
Author: Liwaa Hosh
Author-email: your.email@example.com
Classifier: Programming Language :: Python :: 3
Classifier: License :: OSI Approved :: MIT License
Classifier: Operating System :: OS Independent
Classifier: Topic :: Scientific/Engineering :: Physics
Requires-Python: >=3.7
Dynamic: author
Dynamic: author-email
Dynamic: classifier
Dynamic: description
Dynamic: description-content-type
Dynamic: home-page
Dynamic: requires-python
Dynamic: summary
